gerritbot/__init__.py
gerritbot/bot.py
gerritbot/tests/__init__.py
gerritbot/tests/unit/__init__.py
gerritbot/tests/unit/test_bot.py
gerritbot-0.4.0.dist-info/DESCRIPTION.rst
gerritbot-0.4.0.dist-info/METADATA
gerritbot-0.4.0.dist-info/RECORD
gerritbot-0.4.0.dist-info/WHEEL
gerritbot-0.4.0.dist-info/entry_points.txt
gerritbot-0.4.0.dist-info/metadata.json
gerritbot-0.4.0.dist-info/pbr.json
gerritbot-0.4.0.dist-info/top_level.txt
