Metadata-Version: 2.0
Name: gerritbot
Version: 0.4.0
Summary: Gerrit IRC Bot
Home-page: http://docs.openstack.org/infra/system-config/
Author: OpenStack Infrastructure Team
Author-email: openstack-infra@lists.openstack.org
License: UNKNOWN
Platform: UNKNOWN
Classifier: Intended Audience :: Information Technology
Classifier: Intended Audience :: System Administrators
Classifier: License :: OSI Approved :: Apache Software License
Classifier: Operating System :: POSIX :: Linux
Classifier: Programming Language :: Python
Classifier: Programming Language :: Python :: 2
Classifier: Programming Language :: Python :: 2.7
Classifier: Programming Language :: Python :: 2.6
Requires-Dist: pbr (!=0.7,>=0.6)
Requires-Dist: gerritlib
Requires-Dist: irc
Requires-Dist: pyyaml
Requires-Dist: python-daemon
Requires-Dist: paho-mqtt (>=1.2)
